README.rst
scrapy_memcached_cache.py
setup.py
scrapy_memcached_cache.egg-info/PKG-INFO
scrapy_memcached_cache.egg-info/SOURCES.txt
scrapy_memcached_cache.egg-info/dependency_links.txt
scrapy_memcached_cache.egg-info/not-zip-safe
scrapy_memcached_cache.egg-info/requires.txt
scrapy_memcached_cache.egg-info/top_level.txt