Metadata-Version: 1.1
Name: scrapy-memcached-cache
Version: 0.0.3
Summary: Memcached HTTP cache storage backend for Scrapy
Home-page: https://github.com/cuducos/scrapy-memcached-cache
Author: Eduardo Cuducos
Author-email: cuducos@gmail.com
License: UNKNOWN
Platform: UNKNOWN
Classifier: Development Status :: 4 - Beta
Classifier: Environment :: Plugins
Classifier: Framework :: Scrapy
Classifier: Intended Audience :: Developers
Classifier: License :: OSI Approved :: GNU Lesser General Public License v3 or later (LGPLv3+)
Classifier: Operating System :: OS Independent
Classifier: Programming Language :: Python :: 3 :: Only
